LICENCE
pydoit_nb/__init__.py
pydoit_nb/attrs_helpers.py
pydoit_nb/checklist.py
pydoit_nb/complete.py
pydoit_nb/config_handling.py
pydoit_nb/config_helpers.py
pydoit_nb/config_tools/__init__.py
pydoit_nb/display.py
pydoit_nb/doit_tools.py
pydoit_nb/notebook.py
pydoit_nb/notebook_run.py
pydoit_nb/notebook_step.py
pydoit_nb/py.typed
pydoit_nb/serialization.py
pydoit_nb/tasks_copy_source.py
pydoit_nb/tasks_generation.py
pydoit_nb/testing.py
pydoit_nb/typing.py
pydoit_nb-0.3.4.dist-info/LICENCE
pydoit_nb-0.3.4.dist-info/METADATA
pydoit_nb-0.3.4.dist-info/WHEEL
pydoit_nb-0.3.4.dist-info/RECORD
