Metadata-Version: 2.1
Name: pydoit-nb
Version: 0.3.4
Summary: Library to support combining jupyter notebooks and pydoit.
License: BSD-3-Clause
Author: Zebedee Nicholls
Author-email: zebedee.nicholls@climate-resource.com
Requires-Python: >=3.9,<4.0
Classifier: License :: OSI Approved :: BSD License
Classifier: Programming Language :: Python :: 3
Classifier: Programming Language :: Python :: 3.9
Classifier: Programming Language :: Python :: 3.10
Classifier: Programming Language :: Python :: 3.11
Classifier: Programming Language :: Python :: 3.12
Provides-Extra: notebooks
Requires-Dist: cattrs (>=22.1)
Requires-Dist: doit (>=0.1)
Requires-Dist: jupytext (>=1.0)
Requires-Dist: notebook (>=6.0) ; extra == "notebooks"
Requires-Dist: numpy (>=1.23)
Requires-Dist: papermill (>=2.0)
